depytrace/__init__.py
depytrace/eval/SIR.py
depytrace/eval/__init__.py
depytrace/eval/data.py
depytrace/eval/measures.py
depytrace/eval/tests.py
depytrace/trace/__init__.py
depytrace/trace/backup.py
depytrace/trace/spectral.py
depytrace/trace/trace.py
depytrace/trace/utils/__init__.py
depytrace/trace/utils/heap.py
depytrace-0.0.2.dist-info/METADATA
depytrace-0.0.2.dist-info/WHEEL
depytrace-0.0.2.dist-info/top_level.txt
depytrace-0.0.2.dist-info/RECORD
