Metadata-Version: 2.1
Name: depytrace
Version: 0.0.2
Summary: High conductance rooted trees in relation graphs.
Home-page: https://github.com/maniospas/depytrace
Author: Emmanouil (Manios) Krasanakis
Author-email: maniospas@hotmail.com
License: UNKNOWN
Platform: UNKNOWN
Classifier: Programming Language :: Python :: 3
Classifier: License :: OSI Approved :: Apache Software License
Classifier: Operating System :: OS Independent
Requires-Dist: networkx
